clockify_idleless/Clockify.ico
clockify_idleless/__init__.py
clockify_idleless/clockify.py
clockify_idleless/clockify_to_workbook.py
clockify_idleless/config.ini
clockify_idleless/idleless.py
clockify_idleless-0.1.0.dist-info/LICENSE.txt
clockify_idleless-0.1.0.dist-info/METADATA
clockify_idleless-0.1.0.dist-info/WHEEL
clockify_idleless-0.1.0.dist-info/entry_points.txt
clockify_idleless-0.1.0.dist-info/top_level.txt
clockify_idleless-0.1.0.dist-info/RECORD
