Metadata-Version: 2.1
Name: clockify-idleless
Version: 0.1.0
Summary: Simple Clockify script to track active time
Home-page: https://github.com/dmarcelino/clockify-idleless
Author: Dário Marcelino
Author-email: dario@appscot.com
License: UNKNOWN
Download-URL: https://github.com/dmarcelino/clockify-idleless/archive/v0.1.0.tar.gz
Platform: UNKNOWN
Classifier: Programming Language :: Python :: 3
Classifier: License :: OSI Approved :: MIT License
Classifier: Operating System :: OS Independent
Requires-Python: >=3.5
Requires-Dist: python-dateutil (>=2.8.0)
Requires-Dist: requests (>=2.22.0)
Requires-Dist: wxPython (>=4.0.6)
Requires-Dist: XlsxWriter (>=1.2.2)
